LICENSE
MANIFEST.in
README.txt
setup.py
django_oppia.egg-info/PKG-INFO
django_oppia.egg-info/SOURCES.txt
django_oppia.egg-info/dependency_links.txt
django_oppia.egg-info/requires.txt
django_oppia.egg-info/top_level.txt
docs/.gitignore
docs/Makefile
docs/acknowledgements.rst
docs/api.rst
docs/author.rst
docs/aws.rst
docs/block_install.rst
docs/changelog.rst
docs/changelog_android.rst
docs/changelog_moodleblock.rst
docs/changelog_server.rst
docs/changelog_server_v0.1.rst
docs/changelog_server_v0.2.rst
docs/changelog_server_v0.3.rst
docs/changelog_server_v0.4.rst
docs/changelog_server_v0.5.rst
docs/conf.py
docs/index.rst
docs/install.rst
docs/settings.py
docs/settings.pyc
docs/settings.rst
docs/upgrade.rst
docs/utilities.rst
docs/virtualbox.rst
docs/_build/doctrees/acknowledgements.doctree
docs/_build/doctrees/api.doctree
docs/_build/doctrees/author.doctree
docs/_build/doctrees/aws.doctree
docs/_build/doctrees/block_install.doctree
docs/_build/doctrees/changelog.doctree
docs/_build/doctrees/changelog_android.doctree
docs/_build/doctrees/changelog_moodleblock.doctree
docs/_build/doctrees/changelog_server.doctree
docs/_build/doctrees/changelog_server_v0.1.doctree
docs/_build/doctrees/changelog_server_v0.2.doctree
docs/_build/doctrees/changelog_server_v0.3.doctree
docs/_build/doctrees/changelog_server_v0.4.doctree
docs/_build/doctrees/changelog_server_v0.5.doctree
docs/_build/doctrees/environment.pickle
docs/_build/doctrees/index.doctree
docs/_build/doctrees/install.doctree
docs/_build/doctrees/settings.doctree
docs/_build/doctrees/upgrade.doctree
docs/_build/doctrees/utilities.doctree
docs/_build/doctrees/virtualbox.doctree
docs/_build/doctrees/custom/github.doctree
docs/_build/doctrees/custom/index.doctree
docs/_build/doctrees/custom/manage.doctree
docs/_build/doctrees/custom/client/index.doctree
docs/_build/doctrees/custom/moodle-block/index.doctree
docs/_build/doctrees/custom/server/index.doctree
docs/_build/doctrees/custom/style/index.doctree
docs/_build/doctrees/viz/index.doctree
docs/_build/doctrees/viz/user_map.doctree
docs/_build/html/.buildinfo
docs/_build/html/acknowledgements.html
docs/_build/html/api.html
docs/_build/html/author.html
