Metadata-Version: 1.1
Name: django-oppia
Version: 0.7.2
Summary: Server side component of OppiaMobile learning platform
Home-page: https://digital-campus.org/
Author: Alex Little, Digital Campus
Author-email: alex@digital-campus.org
License: GNU GPL v3 License
Platform: UNKNOWN
Classifier: Environment :: Web Environment
Classifier: Framework :: Django
Classifier: Intended Audience :: Developers
Classifier: License :: OSI Approved :: GNU General Public License v3 (GPLv3)
Classifier: Development Status :: 4 - Beta
Classifier: Operating System :: OS Independent
Classifier: Programming Language :: Python
Classifier: Programming Language :: Python :: 2.6
Classifier: Programming Language :: Python :: 2.7
Classifier: Topic :: Internet :: WWW/HTTP
Classifier: Topic :: Internet :: WWW/HTTP :: Dynamic Content
